mosartwmpy/__init__.py
mosartwmpy/_version.py
mosartwmpy/config_defaults.yaml
mosartwmpy/data_manifest.yaml
mosartwmpy/download.py
mosartwmpy/input_output_variables.py
mosartwmpy/model.py
mosartwmpy/validate.py
mosartwmpy/config/__init__.py
mosartwmpy/config/config.py
mosartwmpy/config/parameters.py
mosartwmpy/farmer_abm/__init__.py
mosartwmpy/farmer_abm/farmer_abm.py
mosartwmpy/grid/__init__.py
mosartwmpy/grid/grid.py
mosartwmpy/hillslope/__init__.py
mosartwmpy/hillslope/routing.py
mosartwmpy/input/__init__.py
mosartwmpy/input/demand.py
mosartwmpy/input/runoff.py
mosartwmpy/main_channel/__init__.py
mosartwmpy/main_channel/irrigation.py
mosartwmpy/main_channel/kinematic_wave.py
mosartwmpy/main_channel/routing.py
mosartwmpy/main_channel/state.py
mosartwmpy/output/__init__.py
mosartwmpy/output/output.py
mosartwmpy/plotting/__init__.py
mosartwmpy/plotting/plot.py
mosartwmpy/reservoirs/__init__.py
mosartwmpy/reservoirs/grid.py
mosartwmpy/reservoirs/istarf.py
mosartwmpy/reservoirs/regulation.py
mosartwmpy/reservoirs/release.py
mosartwmpy/reservoirs/state.py
mosartwmpy/state/__init__.py
mosartwmpy/state/state.py
mosartwmpy/subnetwork/__init__.py
mosartwmpy/subnetwork/irrigation.py
mosartwmpy/subnetwork/routing.py
mosartwmpy/subnetwork/state.py
mosartwmpy/tests/__init__.py
mosartwmpy/tests/demand_1981_01_01.nc
mosartwmpy/tests/dependency_database.parquet
mosartwmpy/tests/grid.zip
mosartwmpy/tests/mean_demand.parquet
mosartwmpy/tests/mean_flow.parquet
mosartwmpy/tests/reservoirs.nc
mosartwmpy/tests/runoff_1981_01_01.nc
mosartwmpy/tests/test_calculate_water_constraints_by_farm.py
mosartwmpy/tests/test_config.yaml
mosartwmpy/tests/test_crop_prices_by_nldas_id.parquet
mosartwmpy/tests/test_epiweek.py
mosartwmpy/tests/test_historic_storage_supply_bias.parquet
mosartwmpy/tests/test_istarf.py
mosartwmpy/tests/test_land_water_constraints_by_farm.parquet
mosartwmpy/tests/test_land_water_constraints_by_farm_live.parquet
mosartwmpy/tests/test_model.py
mosartwmpy-0.6.2.dist-info/LICENSE
mosartwmpy-0.6.2.dist-info/METADATA
mosartwmpy-0.6.2.dist-info/WHEEL
mosartwmpy-0.6.2.dist-info/entry_points.txt
mosartwmpy-0.6.2.dist-info/top_level.txt
mosartwmpy-0.6.2.dist-info/RECORD
