Metadata-Version: 2.1
Name: mosartwmpy
Version: 0.6.2
Summary: Python implementation of MOSART-WM: A water routing and management model
Home-page: https://github.com/IMMM-SFA/mosartwmpy
Author: Travis Thurber
Author-email: travis.thurber@pnnl.gov
License: BSD2-Simplified
Requires-Python: >=3.8,<4.0
License-File: LICENSE
Requires-Dist: bmipy >=2.0
Requires-Dist: click >=8.0.1
Requires-Dist: contextily >=1.2.0
Requires-Dist: dask[complete] >=2021.10.0
Requires-Dist: geopandas >=0.10.2
Requires-Dist: h5netcdf >=0.11.0
Requires-Dist: hvplot >=0.7.3
Requires-Dist: matplotlib >=3.4.3
Requires-Dist: nc-time-axis >=1.4.0
Requires-Dist: netCDF4 >=1.5.7
Requires-Dist: numba >=0.53.1
Requires-Dist: numpy >=1.20.3
Requires-Dist: pandas >=1.3.4
Requires-Dist: pathvalidate >=2.5.0
Requires-Dist: psutil >=5.8.0
Requires-Dist: pyarrow >=6.0.0
Requires-Dist: pyomo >=6.2
Requires-Dist: python-benedict >=0.24.3
Requires-Dist: regex >=2021.10.23
Requires-Dist: requests >=2.26.0
Requires-Dist: rioxarray >=0.8.0
Requires-Dist: tqdm >=4.62.3
Requires-Dist: xarray >=0.19.0
Provides-Extra: dev
Requires-Dist: build >=0.7.0 ; extra == 'dev'
Requires-Dist: nbsphinx >=0.8.7 ; extra == 'dev'
Requires-Dist: recommonmark >=0.7.1 ; extra == 'dev'
Requires-Dist: setuptools >=58.3.0 ; extra == 'dev'
Requires-Dist: sphinx >=4.2.0 ; extra == 'dev'
Requires-Dist: sphinx-panels >=0.6.0 ; extra == 'dev'
Requires-Dist: sphinx-rtd-theme >=1.0.0 ; extra == 'dev'
Requires-Dist: twine >=3.4.2 ; extra == 'dev'
